LICENSE
README.md
setup.cfg
setup.py
ha_nad_receiver.egg-info/PKG-INFO
ha_nad_receiver.egg-info/SOURCES.txt
ha_nad_receiver.egg-info/dependency_links.txt
ha_nad_receiver.egg-info/requires.txt
ha_nad_receiver.egg-info/top_level.txt
ha_nad_receiver.egg-info/zip-safe
nad_receiver/__init__.py
nad_receiver/nad_commands.py
nad_receiver/nad_fake_transport.py
nad_receiver/nad_transport.py