Metadata-Version: 2.1
Name: ha-nad-receiver
Version: 0.3.1
Summary: Library to interface with NAD receivers through RS232, TCP and telnet
Home-page: https://github.com/markoknez/ha_nad_receiver
Author: joopert,markoknez
License: MIT
Download-URL: https://github.com/markoknez/ha_nad_receiver/archive/0.3.1.tar.gz
Platform: UNKNOWN
License-File: LICENSE
